pandas_label_encoder/__init__.py
pandas_label_encoder-1.0.0.dist-info/LICENSE
pandas_label_encoder-1.0.0.dist-info/WHEEL
pandas_label_encoder-1.0.0.dist-info/METADATA
pandas_label_encoder-1.0.0.dist-info/RECORD
