Metadata-Version: 2.1
Name: pandas-label-encoder
Version: 1.0.0
Summary: Label encoder backed by pandas
Home-page: https://github.com/benzerer/pandas-label-encoder
License: MIT
Keywords: pandas,label-encoder,label-encoding,label,encoding,encoder
Author: NOPDANAI DEJVORAKUL
Author-email: b.intm@hotmail.com
Requires-Python: >=3.9,<4.0
Classifier: License :: OSI Approved :: MIT License
Classifier: Programming Language :: Python :: 3
Classifier: Programming Language :: Python :: 3.9
Classifier: Programming Language :: Python :: 3.10
Classifier: Programming Language :: Python :: 3.11
Classifier: Topic :: Software Development :: Libraries :: Python Modules
Requires-Dist: numpy (==1.23.2)
Requires-Dist: pandas (==1.5.2)
Project-URL: Bug Tracker, https://github.com/benzerer/pandas-label-encoder/issues
Project-URL: Documentation, https://github.com/benzerer/pandas-label-encoder
Project-URL: Repository, https://github.com/benzerer/pandas-label-encoder
